zimply_core/__init__.py
zimply_core/zim_core.py
zimply_core-1.0.7.dist-info/LICENSE.txt
zimply_core-1.0.7.dist-info/METADATA
zimply_core-1.0.7.dist-info/WHEEL
zimply_core-1.0.7.dist-info/top_level.txt
zimply_core-1.0.7.dist-info/RECORD
