Metadata-Version: 2.1
Name: zimply-core
Version: 1.0.7
Summary: Fork of ZIMply with only the zimply_core module.
Home-page: https://github.com/dylanmccall/ZIMply-core
Author: Dylan McCall
Author-email: dylan@endlessos.org
License: MIT
Keywords: zim,wiki,wikipedia
Platform: any
Classifier: Programming Language :: Python :: 3.4
Classifier: License :: OSI Approved :: MIT License
Classifier: Development Status :: 2 - Pre-Alpha
License-File: LICENSE.txt
Requires-Dist: zstandard (>=0.14.1)
